README.md
setup.py
chained_mode_time_tool/__init__.py
chained_mode_time_tool.egg-info/PKG-INFO
chained_mode_time_tool.egg-info/SOURCES.txt
chained_mode_time_tool.egg-info/dependency_links.txt
chained_mode_time_tool.egg-info/requires.txt
chained_mode_time_tool.egg-info/top_level.txt